{"airport_code":{"0":"ABE","1":"ABY","2":"ACK","3":"AEX","4":"AGS","5":"ALB","6":"ATL","7":"ATW","8":"AUS","9":"AVL","10":"AZO","11":"BGM","12":"BGR","13":"BHM","14":"BMI","15":"BNA","16":"BOS","17":"BQK","18":"BTR","19":"BTV","20":"BUF","21":"BWI","22":"CAE","23":"CHA","24":"CHO","25":"CHS","26":"CID","27":"CLE","28":"CLT","29":"CMH","30":"CRW","31":"CSG","32":"CVG","33":"CWA","34":"DAY","35":"DCA","36":"DHN","37":"DLH","38":"DSM","39":"DTW","40":"EVV","41":"EWR","42":"EYW","43":"FAY","44":"FSD","45":"FWA","46":"GNV","47":"GPT","48":"GRR","49":"GSO","50":"GSP","51":"GTR","52":"HPN","53":"ILM","54":"IND","55":"ITH","56":"JFK","57":"LAN","58":"LEX","59":"LFT","60":"LGA","61":"MBS","62":"MCI","63":"MEM","64":"MGM","65":"MKE","66":"MLI","67":"MLU","68":"MOB","69":"MOT","70":"MSN","71":"MSP","72":"MYR","73":"OAJ","74":"OMA","75":"ORD","76":"ORF","77":"ORH","78":"PIT","79":"PVD","80":"RDU","81":"RIC","82":"ROA","83":"ROC","84":"RST","85":"SAV","86":"SBN","87":"SDF","88":"SGF","89":"SHV","90":"STL","91":"SYR","92":"TLH","93":"TRI","94":"TVC","95":"TYS","96":"VLD","97":"XNA","98":"ABQ","99":"AMA","100":"ANC","101":"AVP","102":"BDL","103":"BOI","104":"BUR","105":"BZN","106":"COS","107":"DEN","108":"DFW","109":"EGE","110":"ELP","111":"EUG","112":"FAT","113":"FCA","114":"FLL","115":"GEG","116":"HNL","117":"IAD","118":"IAH","119":"ICT","120":"JAX","121":"KOA","122":"LAS","123":"LAX","124":"LBB","125":"LIH","126":"LIT","127":"MCO","128":"MDT","129":"MFE","130":"MIA","131":"MSO","132":"MSY","133":"OGG","134":"OKC","135":"ONT","136":"PBI","137":"PDX","138":"PHL","139":"PHX","140":"PNS","141":"PSP","142":"PWM","143":"RNO","144":"RSW","145":"SAN","146":"SAT","147":"SBA","148":"SEA","149":"SFO","150":"SJC","151":"SJU","152":"SLC","153":"SMF","154":"SNA","155":"SRQ","156":"STT","157":"STX","158":"TPA","159":"TUL","160":"TUS","161":"VPS","162":"ADK","163":"ADQ","164":"AKN","165":"BET","166":"BRW","167":"CDV","168":"DAL","169":"DLG","170":"FAI","171":"GST","172":"JNU","173":"KTN","174":"OAK","175":"OME","176":"OTZ","177":"PAE","178":"PSG","179":"SCC","180":"SIT","181":"WRG","182":"YAK","183":"BQN","184":"HYA","185":"MVY","186":"PSE","187":"BIL","188":"DAB","189":"ECP","190":"FAR","191":"GRB","192":"HOU","193":"HSV","194":"IDA","195":"JAN","196":"MDW","197":"MLB","198":"BIS","199":"BKG","200":"DRO","201":"GJT","202":"HRL","203":"ILG","204":"ISP","205":"SWF","206":"TTN","207":"AZA","208":"BLI","209":"BLV","210":"CAK","211":"CKB","212":"ELM","213":"FNT","214":"GFK","215":"GRI","216":"GTF","217":"HGR","218":"HTS","219":"IAG","220":"LCK","221":"LRD","222":"MFR","223":"MRY","224":"OWB","225":"PBG","226":"PGD","227":"PIA","228":"PIE","229":"PSC","230":"PSM","231":"PVU","232":"RAP","233":"RDM","234":"RFD","235":"SCE","236":"SCK","237":"SFB","238":"SMX","239":"SPI","240":"STC","241":"TOL","242":"USA","243":"ITO","244":"LGB","245":"PPG","246":"ABI","247":"ACT","248":"ALO","249":"BFL","250":"BPT","251":"BRO","252":"CLL","253":"CMI","254":"COU","255":"CRP","256":"DBQ","257":"DRT","258":"FSM","259":"GCK","260":"GGG","261":"GRK","262":"HHH","263":"LAW","264":"LCH","265":"LSE","266":"MAF","267":"MHK","268":"MQT","269":"SBP","270":"SJT","271":"SPS","272":"STS","273":"SWO","274":"TXK","275":"TYR","276":"ACY","277":"LBE","278":"MHT","279":"EWN","280":"LYH","281":"PHF","282":"ABR","283":"ACV","284":"ALS","285":"APN","286":"ASE","287":"BFF","288":"BJI","289":"BRD","290":"BTM","291":"CDC","292":"CGI","293":"CIU","294":"CMX","295":"CNY","296":"COD","297":"CPR","298":"CYS","299":"DDC","300":"DEC","301":"DIK","302":"DVL","303":"EAR","304":"EAU","305":"EKO","306":"ESC","307":"FLG","308":"FOD","309":"GCC","310":"GUC","311":"HDN","312":"HIB","313":"HLN","314":"HOB","315":"HYS","316":"IMT","317":"INL","318":"JLN","319":"JMS","320":"JST","321":"LAR","322":"LBF","323":"LBL","324":"LNK","325":"LWB","326":"LWS","327":"MCW","328":"MEI","329":"MKG","330":"MTJ","331":"OGS","332":"OTH","333":"PAH","334":"PIB","335":"PIH","336":"PLN","337":"PRC","338":"PUB","339":"RDD","340":"RHI","341":"RIW","342":"RKS","343":"ROW","344":"SAF","345":"SGU","346":"SHD","347":"SHR","348":"SLN","349":"SUN","350":"SUX","351":"TBN","352":"TWF","353":"VCT","354":"VEL","355":"WYS","356":"XWA","357":"YUM","358":"ALW","359":"EAT","360":"PUW","361":"YKM","362":"GUM","363":"SPN","364":"JAC","365":"OGD","366":"ERI","367":"BIH","368":"ATY","369":"PIR","370":"HVN","371":"CDB","372":"IPT","373":"BFM","374":"MMH","375":"UIN","376":"PGV","377":"ISN","378":"ART","379":"YNG","380":"IFP","381":"FNL","382":"UST","383":"TKI","384":"ENV","385":"EFD","386":"CLD","387":"CEC","388":"MCN","389":"CIC","390":"FOE","391":"LMT","392":"MOD","393":"IYK","394":"IPL","395":"TUP","396":"UTM","397":"TEX","398":"FLO","399":"MWH","400":"OXR","401":"PFN","402":"PMD","403":"SLE","404":"SOP","405":"APF","406":"MTH","407":"MKC","408":"GLH","409":"ISO","410":"RCA","411":"HKY","412":"VIS","413":"FMN","414":"LNY","415":"MKK","416":"ILE","417":"SKA","418":"CBM","419":"DUT"},"location":{"0":"Allentown\/Bethlehem\/Easton, PA","1":"Albany, GA","2":"Nantucket, MA","3":"Alexandria, LA","4":"Augusta, GA","5":"Albany, NY","6":"Atlanta, GA","7":"Appleton, WI","8":"Austin, TX","9":"Asheville, NC","10":"Kalamazoo, MI","11":"Binghamton, NY","12":"Bangor, ME","13":"Birmingham, AL","14":"Bloomington\/Normal, IL","15":"Nashville, TN","16":"Boston, MA","17":"Brunswick, GA","18":"Baton Rouge, LA","19":"Burlington, VT","20":"Buffalo, NY","21":"Baltimore, MD","22":"Columbia, SC","23":"Chattanooga, TN","24":"Charlottesville, VA","25":"Charleston, SC","26":"Cedar Rapids\/Iowa City, IA","27":"Cleveland, OH","28":"Charlotte, NC","29":"Columbus, OH","30":"Charleston\/Dunbar, WV","31":"Columbus, GA","32":"Cincinnati, OH","33":"Mosinee, WI","34":"Dayton, OH","35":"Washington, DC","36":"Dothan, AL","37":"Duluth, MN","38":"Des Moines, IA","39":"Detroit, MI","40":"Evansville, IN","41":"Newark, NJ","42":"Key West, FL","43":"Fayetteville, NC","44":"Sioux Falls, SD","45":"Fort Wayne, IN","46":"Gainesville, FL","47":"Gulfport\/Biloxi, MS","48":"Grand Rapids, MI","49":"Greensboro\/High Point, NC","50":"Greer, SC","51":"Columbus, MS","52":"White Plains, NY","53":"Wilmington, NC","54":"Indianapolis, IN","55":"Ithaca\/Cortland, NY","56":"New York, NY","57":"Lansing, MI","58":"Lexington, KY","59":"Lafayette, LA","60":"New York, NY","61":"Saginaw\/Bay City\/Midland, MI","62":"Kansas City, MO","63":"Memphis, TN","64":"Montgomery, AL","65":"Milwaukee, WI","66":"Moline, IL","67":"Monroe, LA","68":"Mobile, AL","69":"Minot, ND","70":"Madison, WI","71":"Minneapolis, MN","72":"Myrtle Beach, SC","73":"Jacksonville\/Camp Lejeune, NC","74":"Omaha, NE","75":"Chicago, IL","76":"Norfolk, VA","77":"Worcester, MA","78":"Pittsburgh, PA","79":"Providence, RI","80":"Raleigh\/Durham, NC","81":"Richmond, VA","82":"Roanoke, VA","83":"Rochester, NY","84":"Rochester, MN","85":"Savannah, GA","86":"South Bend, IN","87":"Louisville, KY","88":"Springfield, MO","89":"Shreveport, LA","90":"St. Louis, MO","91":"Syracuse, NY","92":"Tallahassee, FL","93":"Bristol\/Johnson City\/Kingsport, TN","94":"Traverse City, MI","95":"Knoxville, TN","96":"Valdosta, GA","97":"Fayetteville, AR","98":"Albuquerque, NM","99":"Amarillo, TX","100":"Anchorage, AK","101":"Scranton\/Wilkes-Barre, PA","102":"Hartford, CT","103":"Boise, ID","104":"Burbank, CA","105":"Bozeman, MT","106":"Colorado Springs, CO","107":"Denver, CO","108":"Dallas\/Fort Worth, TX","109":"Eagle, CO","110":"El Paso, TX","111":"Eugene, OR","112":"Fresno, CA","113":"Kalispell, MT","114":"Fort Lauderdale, FL","115":"Spokane, WA","116":"Honolulu, HI","117":"Washington, DC","118":"Houston, TX","119":"Wichita, KS","120":"Jacksonville, FL","121":"Kona, HI","122":"Las Vegas, NV","123":"Los Angeles, CA","124":"Lubbock, TX","125":"Lihue, HI","126":"Little Rock, AR","127":"Orlando, FL","128":"Harrisburg, PA","129":"Mission\/McAllen\/Edinburg, TX","130":"Miami, FL","131":"Missoula, MT","132":"New Orleans, LA","133":"Kahului, HI","134":"Oklahoma City, OK","135":"Ontario, CA","136":"West Palm Beach\/Palm Beach, FL","137":"Portland, OR","138":"Philadelphia, PA","139":"Phoenix, AZ","140":"Pensacola, FL","141":"Palm Springs, CA","142":"Portland, ME","143":"Reno, NV","144":"Fort Myers, FL","145":"San Diego, CA","146":"San Antonio, TX","147":"Santa Barbara, CA","148":"Seattle, WA","149":"San Francisco, CA","150":"San Jose, CA","151":"San Juan, PR","152":"Salt Lake City, UT","153":"Sacramento, CA","154":"Santa Ana, CA","155":"Sarasota\/Bradenton, FL","156":"Charlotte Amalie, VI","157":"Christiansted, VI","158":"Tampa, FL","159":"Tulsa, OK","160":"Tucson, AZ","161":"Valparaiso, FL","162":"Adak Island, AK","163":"Kodiak, AK","164":"King Salmon, AK","165":"Bethel, AK","166":"Barrow, AK","167":"Cordova, AK","168":"Dallas, TX","169":"Dillingham, AK","170":"Fairbanks, AK","171":"Gustavus, AK","172":"Juneau, AK","173":"Ketchikan, AK","174":"Oakland, CA","175":"Nome, AK","176":"Kotzebue, AK","177":"Everett, WA","178":"Petersburg, AK","179":"Deadhorse, AK","180":"Sitka, AK","181":"Wrangell, AK","182":"Yakutat, AK","183":"Aguadilla, PR","184":"Hyannis, MA","185":"Martha's Vineyard, MA","186":"Ponce, PR","187":"Billings, MT","188":"Daytona Beach, FL","189":"Panama City, FL","190":"Fargo, ND","191":"Green Bay, WI","192":"Houston, TX","193":"Huntsville, AL","194":"Idaho Falls, ID","195":"Jackson\/Vicksburg, MS","196":"Chicago, IL","197":"Melbourne, FL","198":"Bismarck\/Mandan, ND","199":"Branson, MO","200":"Durango, CO","201":"Grand Junction, CO","202":"Harlingen\/San Benito, TX","203":"Wilmington, DE","204":"Islip, NY","205":"Newburgh\/Poughkeepsie, NY","206":"Trenton, NJ","207":"Phoenix, AZ","208":"Bellingham, WA","209":"Belleville, IL","210":"Akron, OH","211":"Clarksburg\/Fairmont, WV","212":"Elmira\/Corning, NY","213":"Flint, MI","214":"Grand Forks, ND","215":"Grand Island, NE","216":"Great Falls, MT","217":"Hagerstown, MD","218":"Ashland, WV","219":"Niagara Falls, NY","220":"Columbus, OH","221":"Laredo, TX","222":"Medford, OR","223":"Monterey, CA","224":"Owensboro, KY","225":"Plattsburgh, NY","226":"Punta Gorda, FL","227":"Peoria, IL","228":"St. Petersburg, FL","229":"Pasco\/Kennewick\/Richland, WA","230":"Portsmouth, NH","231":"Provo, UT","232":"Rapid City, SD","233":"Bend\/Redmond, OR","234":"Rockford, IL","235":"State College, PA","236":"Stockton, CA","237":"Sanford, FL","238":"Santa Maria, CA","239":"Springfield, IL","240":"St. Cloud, MN","241":"Toledo, OH","242":"Concord, NC","243":"Hilo, HI","244":"Long Beach, CA","245":"Pago Pago, TT","246":"Abilene, TX","247":"Waco, TX","248":"Waterloo, IA","249":"Bakersfield, CA","250":"Beaumont\/Port Arthur, TX","251":"Brownsville, TX","252":"College Station\/Bryan, TX","253":"Champaign\/Urbana, IL","254":"Columbia, MO","255":"Corpus Christi, TX","256":"Dubuque, IA","257":"Del Rio, TX","258":"Fort Smith, AR","259":"Garden City, KS","260":"Longview, TX","261":"Killeen, TX","262":"Hilton Head, SC","263":"Lawton\/Fort Sill, OK","264":"Lake Charles, LA","265":"La Crosse, WI","266":"Midland\/Odessa, TX","267":"Manhattan\/Ft. Riley, KS","268":"Marquette, MI","269":"San Luis Obispo, CA","270":"San Angelo, TX","271":"Wichita Falls, TX","272":"Santa Rosa, CA","273":"Stillwater, OK","274":"Texarkana, AR","275":"Tyler, TX","276":"Atlantic City, NJ","277":"Latrobe, PA","278":"Manchester, NH","279":"New Bern\/Morehead\/Beaufort, NC","280":"Lynchburg, VA","281":"Newport News\/Williamsburg, VA","282":"Aberdeen, SD","283":"Arcata\/Eureka, CA","284":"Alamosa, CO","285":"Alpena, MI","286":"Aspen, CO","287":"Scottsbluff, NE","288":"Bemidji, MN","289":"Brainerd, MN","290":"Butte, MT","291":"Cedar City, UT","292":"Cape Girardeau, MO","293":"Sault Ste. Marie, MI","294":"Hancock\/Houghton, MI","295":"Moab, UT","296":"Cody, WY","297":"Casper, WY","298":"Cheyenne, WY","299":"Dodge City, KS","300":"Decatur, IL","301":"Dickinson, ND","302":"Devils Lake, ND","303":"Kearney, NE","304":"Eau Claire, WI","305":"Elko, NV","306":"Escanaba, MI","307":"Flagstaff, AZ","308":"Fort Dodge, IA","309":"Gillette, WY","310":"Gunnison, CO","311":"Hayden, CO","312":"Hibbing, MN","313":"Helena, MT","314":"Hobbs, NM","315":"Hays, KS","316":"Iron Mountain\/Kingsfd, MI","317":"International Falls, MN","318":"Joplin, MO","319":"Jamestown, ND","320":"Johnstown, PA","321":"Laramie, WY","322":"North Platte, NE","323":"Liberal, KS","324":"Lincoln, NE","325":"Lewisburg, WV","326":"Lewiston, ID","327":"Mason City, IA","328":"Meridian, MS","329":"Muskegon, MI","330":"Montrose\/Delta, CO","331":"Ogdensburg, NY","332":"North Bend\/Coos Bay, OR","333":"Paducah, KY","334":"Hattiesburg\/Laurel, MS","335":"Pocatello, ID","336":"Pellston, MI","337":"Prescott, AZ","338":"Pueblo, CO","339":"Redding, CA","340":"Rhinelander, WI","341":"Riverton\/Lander, WY","342":"Rock Springs, WY","343":"Roswell, NM","344":"Santa Fe, NM","345":"St. George, UT","346":"Staunton, VA","347":"Sheridan, WY","348":"Salina, KS","349":"Sun Valley\/Hailey\/Ketchum, ID","350":"Sioux City, IA","351":"Fort Leonard Wood, MO","352":"Twin Falls, ID","353":"Victoria, TX","354":"Vernal, UT","355":"West Yellowstone, MT","356":"Williston, ND","357":"Yuma, AZ","358":"Walla Walla, WA","359":"Wenatchee, WA","360":"Pullman, WA","361":"Yakima, WA","362":"Guam, TT","363":"Saipan, TT","364":"Jackson, WY","365":"Ogden, UT","366":"Erie, PA","367":"Bishop, CA","368":"Watertown, SD","369":"Pierre, SD","370":"New Haven, CT","371":"Cold Bay, AK","372":"Williamsport, PA","373":"Mobile, AL","374":"Mammoth Lakes, CA","375":"Quincy, IL","376":"Greenville, NC","377":"Williston, ND","378":"Watertown, NY","379":"Youngstown\/Warren, OH","380":"Bullhead City, AZ","381":"Fort Collins\/Loveland, CO","382":"St. Augustine, FL","383":"Tokeen, AK","384":"Wendover, UT","385":"Houston, TX","386":"Carlsbad, CA","387":"Crescent City, CA","388":"Macon, GA","389":"Chico, CA","390":"Topeka, KS","391":"Klamath Falls, OR","392":"Modesto, CA","393":"Inyokern, CA","394":"El Centro, CA","395":"Tupelo, MS","396":"Tunica, MS","397":"Telluride, CO","398":"Florence, SC","399":"Moses Lake, WA","400":"Oxnard\/Ventura, CA","401":"Panama City, FL","402":"Palmdale, CA","403":"Salem, OR","404":"Pinehurst\/Southern Pines, NC","405":"Naples, FL","406":"Marathon, FL","407":"Kansas City, MO","408":"Greenville, MS","409":"Kinston, NC","410":"Rapid City, SD","411":"Hickory, NC","412":"Visalia, CA","413":"Farmington, NM","414":"Lanai, HI","415":"Hoolehua, HI","416":"Killeen, TX","417":"Spokane, WA","418":"Columbus, MS","419":"Unalaska, AK"},"name":{"0":" Lehigh Valley International","1":" Southwest Georgia Regional","2":" Nantucket Memorial","3":" Alexandria International","4":" Augusta Regional at Bush Field","5":" Albany International","6":" Hartsfield-Jackson Atlanta International","7":" Appleton International","8":" Austin - Bergstrom International","9":" Asheville Regional","10":" Kalamazoo\/Battle Creek International","11":" Greater Binghamton\/Edwin A. Link Field","12":" Bangor International","13":" Birmingham-Shuttlesworth International","14":" Central Il Regional Airport at Bloomington","15":" Nashville International","16":" Logan International","17":" Brunswick Golden Isles","18":" Baton Rouge Metropolitan\/Ryan Field","19":" Burlington International","20":" Buffalo Niagara International","21":" Baltimore\/Washington International Thurgood Marshall","22":" Columbia Metropolitan","23":" Lovell Field","24":" Charlottesville Albemarle","25":" Charleston AFB\/International","26":" The Eastern Iowa","27":" Cleveland-Hopkins International","28":" Charlotte Douglas International","29":" John Glenn Columbus International","30":" Yeager","31":" Columbus Airport","32":" Cincinnati\/Northern Kentucky International","33":" Central Wisconsin","34":" James M Cox\/Dayton International","35":" Ronald Reagan Washington National","36":" Dothan Regional","37":" Duluth International","38":" Des Moines International","39":" Detroit Metro Wayne County","40":" Evansville Regional","41":" Newark Liberty International","42":" Key West International","43":" Fayetteville Regional\/Grannis Field","44":" Joe Foss Field","45":" Fort Wayne International","46":" Gainesville Regional","47":" Gulfport-Biloxi International","48":" Gerald R. Ford International","49":" Piedmont Triad International","50":" Greenville-Spartanburg International","51":" Golden Triangle Regional","52":" Westchester County","53":" Wilmington International","54":" Indianapolis International","55":" Ithaca Tompkins Regional","56":" John F. Kennedy International","57":" Capital Region International","58":" Blue Grass","59":" Lafayette Regional Paul Fournet Field","60":" LaGuardia","61":" MBS International","62":" Kansas City International","63":" Memphis International","64":" Montgomery Regional","65":" General Mitchell International","66":" Quad City International","67":" Monroe Regional","68":" Mobile Regional","69":" Minot International","70":" Dane County Regional-Truax Field","71":" Minneapolis-St Paul International","72":" Myrtle Beach International","73":" Albert J Ellis","74":" Eppley Airfield","75":" Chicago O'Hare International","76":" Norfolk International","77":" Worcester Regional","78":" Pittsburgh International","79":" Theodore Francis Green State","80":" Raleigh-Durham International","81":" Richmond International","82":" Roanoke Blacksburg Regional Woodrum Field","83":" Greater Rochester International","84":" Rochester International","85":" Savannah\/Hilton Head International","86":" South Bend International","87":" Louisville Muhammad Ali International","88":" Springfield-Branson National","89":" Shreveport Regional","90":" St Louis Lambert International","91":" Syracuse Hancock International","92":" Tallahassee International","93":" Tri Cities","94":" Cherry Capital","95":" McGhee Tyson","96":" Valdosta Regional","97":" Northwest Arkansas Regional","98":" Albuquerque International Sunport","99":" Rick Husband Amarillo International","100":" Ted Stevens Anchorage International","101":" Wilkes Barre Scranton International","102":" Bradley International","103":" Boise Air Terminal","104":" Bob Hope","105":" Bozeman Yellowstone International","106":" City of Colorado Springs Municipal","107":" Denver International","108":" Dallas\/Fort Worth International","109":" Eagle County Regional","110":" El Paso International","111":" Mahlon Sweet Field","112":" Fresno Yosemite International","113":" Glacier Park International","114":" Fort Lauderdale-Hollywood International","115":" Spokane International","116":" Daniel K Inouye International","117":" Washington Dulles International","118":" George Bush Intercontinental\/Houston","119":" Wichita Dwight D Eisenhower National","120":" Jacksonville International","121":" Ellison Onizuka Kona International at Keahole","122":" McCarran International","123":" Los Angeles International","124":" Lubbock Preston Smith International","125":" Lihue Airport","126":" Bill and Hillary Clinton Nat Adams Field","127":" Orlando International","128":" Harrisburg International","129":" McAllen Miller International","130":" Miami International","131":" Missoula International","132":" Louis Armstrong New Orleans International","133":" Kahului Airport","134":" Will Rogers World","135":" Ontario International","136":" Palm Beach International","137":" Portland International","138":" Philadelphia International","139":" Phoenix Sky Harbor International","140":" Pensacola International","141":" Palm Springs International","142":" Portland International Jetport","143":" Reno\/Tahoe International","144":" Southwest Florida International","145":" San Diego International","146":" San Antonio International","147":" Santa Barbara Municipal","148":" Seattle\/Tacoma International","149":" San Francisco International","150":" Norman Y. Mineta San Jose International","151":" Luis Munoz Marin International","152":" Salt Lake City International","153":" Sacramento International","154":" John Wayne Airport-Orange County","155":" Sarasota\/Bradenton International","156":" Cyril E King","157":" Henry E. Rohlsen","158":" Tampa International","159":" Tulsa International","160":" Tucson International","161":" Eglin AFB Destin Fort Walton Beach","162":" Adak","163":" Kodiak Airport","164":" King Salmon Airport","165":" Bethel Airport","166":" Wiley Post\/Will Rogers Memorial","167":" Merle K Mudhole Smith","168":" Dallas Love Field","169":" Dillingham Airport","170":" Fairbanks International","171":" Gustavus Airport","172":" Juneau International","173":" Ketchikan International","174":" Metropolitan Oakland International","175":" Nome Airport","176":" Ralph Wien Memorial","177":" Snohomish County","178":" Petersburg James A Johnson","179":" Deadhorse Airport","180":" Sitka Rocky Gutierrez","181":" Wrangell Airport","182":" Yakutat Airport","183":" Rafael Hernandez","184":" Barnstable Municipal-Boardman\/Polando Field","185":" Martha's Vineyard Airport","186":" Mercedita","187":" Billings Logan International","188":" Daytona Beach International","189":" Northwest Florida Beaches International","190":" Hector International","191":" Green Bay Austin Straubel International","192":" William P Hobby","193":" Huntsville International-Carl T Jones Field","194":" Idaho Falls Regional","195":" Jackson Medgar Wiley Evers International","196":" Chicago Midway International","197":" Melbourne International","198":" Bismarck Municipal","199":" Branson Airport","200":" Durango La Plata County","201":" Grand Junction Regional","202":" Valley International","203":" New Castle","204":" Long Island MacArthur","205":" New York Stewart International","206":" Trenton Mercer","207":" Phoenix - Mesa Gateway","208":" Bellingham International","209":" Scott AFB\/MidAmerica","210":" Akron-Canton Regional","211":" North Central West Virginia","212":" Elmira\/Corning Regional","213":" Bishop International","214":" Grand Forks International","215":" Central Nebraska Regional","216":" Great Falls International","217":" Hagerstown Regional-Richard A. Henson Field","218":" Tri-State\/Milton J. Ferguson Field","219":" Niagara Falls International","220":" Rickenbacker International","221":" Laredo International","222":" Rogue Valley International - Medford","223":" Monterey Regional","224":" Owensboro Daviess County Regional","225":" Plattsburgh International","226":" Punta Gorda Airport","227":" General Downing - Peoria International","228":" St Pete Clearwater International","229":" Tri Cities","230":" Portsmouth International at Pease","231":" Provo Municipal","232":" Rapid City Regional","233":" Roberts Field","234":" Chicago\/Rockford International","235":" University Park","236":" Stockton Metropolitan","237":" Orlando Sanford International","238":" Santa Maria Public\/Capt. G. Allan Hancock Field","239":" Abraham Lincoln Capital","240":" St. Cloud Regional","241":" Toledo Express","242":" Concord Padgett Regional","243":" Hilo International","244":" Long Beach Airport","245":" Pago Pago International","246":" Abilene Regional","247":" Waco Regional","248":" Waterloo Regional","249":" Meadows Field","250":" Jack Brooks Regional","251":" Brownsville South Padre Island International","252":" Easterwood Field","253":" University of Illinois\/Willard","254":" Columbia Regional","255":" Corpus Christi International","256":" Dubuque Regional","257":" Del Rio International","258":" Fort Smith Regional","259":" Garden City Regional","260":" East Texas Regional","261":" Robert Gray AAF","262":" Hilton Head Airport","263":" Lawton-Fort Sill Regional","264":" Lake Charles Regional","265":" La Crosse Regional","266":" Midland International Air and Space Port","267":" Manhattan Regional","268":" Sawyer International","269":" San Luis County Regional","270":" San Angelo Regional\/Mathis Field","271":" Sheppard AFB\/Wichita Falls Municipal","272":" Charles M. Schulz - Sonoma County","273":" Stillwater Regional","274":" Texarkana Regional-Webb Field","275":" Tyler Pounds Regional","276":" Atlantic City International","277":" Arnold Palmer Regional","278":" Manchester-Boston Regional","279":" Coastal Carolina Regional","280":" Lynchburg Regional\/Preston Glenn Field","281":" Newport News\/Williamsburg International","282":" Aberdeen Regional","283":" California Redwood Coast Humboldt County","284":" San Luis Valley Regional\/Bergman Field","285":" Alpena County Regional","286":" Aspen Pitkin County Sardy Field","287":" Western Neb. Regional\/William B. Heilig Field","288":" Bemidji Regional","289":" Brainerd Lakes Regional","290":" Bert Mooney","291":" Cedar City Regional","292":" Cape Girardeau Regional","293":" Chippewa County International","294":" Houghton County Memorial","295":" Canyonlands Field","296":" Yellowstone Regional","297":" Casper\/Natrona County International","298":" Cheyenne Regional\/Jerry Olson Field","299":" Dodge City Regional","300":" Decatur Airport","301":" Dickinson - Theodore Roosevelt Regional","302":" Devils Lake Regional","303":" Kearney Regional","304":" Chippewa Valley Regional","305":" Elko Regional","306":" Delta County","307":" Flagstaff Pulliam","308":" Fort Dodge Regional","309":" Gillette Campbell County","310":" Gunnison-Crested Butte Regional","311":" Yampa Valley","312":" Range Regional","313":" Helena Regional","314":" Lea County Regional","315":" Hays Regional","316":" Ford","317":" Falls International Einarson Field","318":" Joplin Regional","319":" Jamestown Regional","320":" John Murtha Johnstown-Cambria County","321":" Laramie Regional","322":" North Platte Regional Airport Lee Bird Field","323":" Liberal Mid-America Regional","324":" Lincoln Airport","325":" Greenbrier Valley","326":" Lewiston Nez Perce County","327":" Mason City Municipal","328":" Key Field","329":" Muskegon County","330":" Montrose Regional","331":" Ogdensburg International","332":" Southwest Oregon Regional","333":" Barkley Regional","334":" Hattiesburg-Laurel Regional","335":" Pocatello Regional","336":" Pellston Regional Airport of Emmet County","337":" Prescott Regional Ernest A Love Field","338":" Pueblo Memorial","339":" Redding Municipal","340":" Rhinelander\/Oneida County","341":" Riverton Regional","342":" Southwest Wyoming Regional","343":" Roswell International Air Center","344":" Santa Fe Municipal","345":" St George Regional","346":" Shenandoah Valley Regional","347":" Sheridan County","348":" Salina Regional","349":" Friedman Memorial","350":" Sioux Gateway Brig Gen Bud Day Field","351":" Waynesville-St. Robert Regional Forney Field","352":" Joslin Field - Magic Valley Regional","353":" Victoria Regional","354":" Vernal Regional","355":" Yellowstone","356":" Williston Basin International","357":" Yuma MCAS\/Yuma International","358":" Walla Walla Regional","359":" Pangborn Memorial","360":" Pullman Moscow Regional","361":" Yakima Air Terminal\/McAllister Field","362":" Guam International","363":" Francisco C. Ada Saipan International","364":" Jackson Hole","365":" Ogden-Hinckley","366":" Erie International\/Tom Ridge Field","367":" Bishop Airport","368":" Watertown Regional","369":" Pierre Regional","370":" Tweed New Haven","371":" Cold Bay Airport","372":" Williamsport Regional","373":" Mobile Downtown","374":" Mammoth Lakes Airport","375":" Quincy Regional-Baldwin Field","376":" Pitt Greenville","377":" Sloulin Field International","378":" Watertown International","379":" Youngstown-Warren Regional","380":" Laughlin\/Bullhead International","381":" Northern Colorado Regional","382":" Northeast Florida Regional","383":" Tokeen Airport","384":" Wendover Airport","385":" Ellington","386":" McClellan-Palomar","387":" Jack McNamara Field","388":" Middle Georgia Regional","389":" Chico Municipal","390":" Topeka Regional","391":" Crater Lake Klamath Regional","392":" Modesto City-County-Harry Sham Field","393":" Inyokern Airport","394":" Imperial County","395":" Tupelo Regional","396":" Tunica Municipal","397":" Telluride Regional","398":" Florence Regional","399":" Grant County International","400":" Oxnard","401":" Bay County","402":" Palmdale USAF Plant 42","403":" McNary Field","404":" Moore County","405":" Naples Municipal","406":" The Florida Keys Marathon International","407":" Charles B. Wheeler Downtown","408":" Greenville Mid Delta","409":" Kinston Regional Jetport at Stallings Field","410":" Ellsworth AFB","411":" Hickory Regional","412":" Visalia Municipal","413":" Four Corners Regional","414":" Lanai Airport","415":" Molokai","416":" Skylark Field","417":" Fairchild AFB","418":" Columbus AFB","419":" Unalaska Airport"},"latitude":{"0":40.6022939,"1":31.5785074,"2":41.2834704,"3":31.3112936,"4":33.4734978,"5":42.6525793,"6":33.748752,"7":44.2619309,"8":30.267153,"9":35.5950581,"10":42.2917069,"11":42.0986867,"12":44.8016128,"13":33.5185892,"14":40.5478429,"15":36.1626638,"16":42.3600825,"17":31.1499528,"18":30.4514677,"19":44.4758825,"20":42.8864468,"21":39.2903848,"22":34.0007104,"23":35.0457984,"24":38.0293059,"25":32.7764749,"26":41.9778795,"27":41.49932,"28":35.2270869,"29":39.9611755,"30":38.3606509,"31":32.4609764,"32":39.1031182,"33":44.7930232,"34":39.7589478,"35":38.9071923,"36":31.2232313,"37":46.7866719,"38":41.5868353,"39":42.331427,"40":37.9715592,"41":40.735657,"42":24.5554183,"43":35.0526641,"44":43.5460223,"45":41.079273,"46":29.6516344,"47":30.3674198,"48":42.9633599,"49":35.9864557,"50":34.9387279,"51":33.4956744,"52":41.0339862,"53":34.2103894,"54":39.768403,"55":42.6011813,"56":40.7127753,"57":42.732535,"58":38.0405837,"59":30.2240897,"60":40.7127753,"61":43.6155825,"62":39.0997265,"63":35.1495343,"64":32.3792233,"65":43.0389025,"66":41.5067003,"67":32.5093109,"68":30.6953657,"69":48.2329668,"70":43.0721661,"71":44.977753,"72":33.6890603,"73":34.7540524,"74":41.2565369,"75":41.8781136,"76":36.8507689,"77":42.2625932,"78":40.4406248,"79":41.8239891,"80":35.9940329,"81":37.5407246,"82":37.2709704,"83":43.1565779,"84":44.0121221,"85":32.0808989,"86":41.6763545,"87":38.2526647,"88":37.2089572,"89":32.5251516,"90":38.6270025,"91":43.0481221,"92":30.4382559,"93":36.2939205,"94":44.7630567,"95":35.9606384,"96":30.8327022,"97":36.0626579,"98":35.0843859,"99":35.2219971,"100":61.2175758,"101":41.2981769,"102":41.7658043,"103":43.6150186,"104":34.1808392,"105":45.6814733,"106":38.8338816,"107":39.7392358,"108":32.7078751,"109":39.6542086,"110":31.7618778,"111":44.0520691,"112":36.7377981,"113":48.1919889,"114":26.1224386,"115":47.6587802,"116":21.3098845,"117":38.9071923,"118":29.7604267,"119":37.6871761,"120":30.3321838,"121":19.6419129,"122":36.171563,"123":34.0522342,"124":33.5778631,"125":21.9742235,"126":34.7444618,"127":28.5383832,"128":40.2731911,"129":26.2336971,"130":25.7616798,"131":46.8721284,"132":29.9510658,"133":20.8893016,"134":35.4675602,"135":34.0633443,"136":26.7153424,"137":45.515232,"138":39.9525839,"139":33.4483771,"140":30.421309,"141":33.8302961,"142":43.6590993,"143":39.529919,"144":26.640628,"145":32.715738,"146":29.4251905,"147":34.4208305,"148":47.6062095,"149":37.7749295,"150":37.33874,"151":18.4670588,"152":40.7607793,"153":38.5815719,"154":33.7454725,"155":27.336465,"156":18.3419004,"157":17.7466397,"158":27.950575,"159":36.1539816,"160":32.2539787,"161":30.5085309,"162":51.7615874,"163":57.79,"164":58.6887106,"165":60.794259,"166":71.2905556,"167":60.5424087,"168":32.7766642,"169":59.0395277,"170":64.8400511,"171":58.4126017,"172":58.3004933,"173":55.3422222,"174":37.8043514,"175":64.5005909,"176":66.8969151,"177":47.9789848,"178":56.8124542,"179":70.2001996,"180":57.0532193,"181":56.4706104,"182":59.5453393,"183":18.4274454,"184":41.6524911,"185":41.3804981,"186":18.0110768,"187":45.7832856,"188":29.2108147,"189":30.1588129,"190":46.8771863,"191":44.5133188,"192":29.7604267,"193":34.7303688,"194":43.4926607,"195":32.3522304,"196":41.8781136,"197":28.0836269,"198":46.8266603,"199":36.6436731,"200":37.27528,"201":39.0638705,"202":26.132576,"203":39.744655,"204":40.7298207,"205":41.5034271,"206":40.2205824,"207":33.4483771,"208":48.7519112,"209":38.5200504,"210":41.0814447,"211":39.4850848,"212":42.1607628,"213":43.0125274,"214":47.9252568,"215":40.9263957,"216":47.5052849,"217":39.6417629,"218":37.4084488,"219":43.0962143,"220":39.9611755,"221":27.5035613,"222":42.3265152,"223":36.6002378,"224":37.7719074,"225":44.6994873,"226":26.9297836,"227":40.6936488,"228":27.7676008,"229":46.2086683,"230":43.0717552,"231":40.2338438,"232":44.0805434,"233":44.0581728,"234":42.2711311,"235":40.7933949,"236":37.9577016,"237":28.8028612,"238":34.9530337,"239":39.7817213,"240":45.5579451,"241":41.6528052,"242":35.4087517,"243":19.7216023,"244":33.7700504,"245":-14.2756319,"246":32.4487364,"247":31.549333,"248":42.492786,"249":35.3732921,"250":30.080174,"251":25.9017472,"252":30.825147,"253":40.1164204,"254":38.9517053,"255":27.8005828,"256":42.506348,"257":29.3708857,"258":35.3843722,"259":37.9716898,"260":32.5007037,"261":31.1171194,"262":32.216316,"263":34.5938359,"264":30.2265949,"265":43.8137751,"266":31.9391746,"267":39.1836082,"268":46.5436199,"269":35.2827524,"270":31.4637723,"271":33.9137085,"272":38.440429,"273":36.1156071,"274":33.4304827,"275":32.3512601,"276":39.3642834,"277":40.3211808,"278":42.9956397,"279":35.108493,"280":37.4137536,"281":37.2707022,"282":45.4646985,"283":40.9709197,"284":37.4694491,"285":45.0616794,"286":39.1910983,"287":41.8666341,"288":47.471573,"289":46.3526733,"290":46.0038232,"291":37.6774769,"292":37.3058839,"293":46.4977115,"294":47.1268714,"295":38.5733155,"296":44.5263422,"297":42.848709,"298":41.1399814,"299":37.7527982,"300":39.8403147,"301":46.8791756,"302":48.112779,"303":40.6993303,"304":44.811349,"305":40.8324211,"306":45.7452466,"307":35.1982836,"308":42.4974694,"309":44.2910915,"310":38.5458246,"311":40.4894302,"312":47.4271546,"313":46.5891452,"314":32.7026116,"315":38.8791783,"316":45.7949561,"317":48.6023149,"318":37.0842271,"319":46.9105438,"320":40.3267407,"321":41.3113669,"322":41.1402759,"323":37.0430812,"324":40.813616,"325":37.8017879,"326":46.4004089,"327":43.1535728,"328":32.3643098,"329":43.2341813,"330":38.4783198,"331":44.6942291,"332":43.4065012,"333":37.0833893,"334":31.3271189,"335":42.8621042,"336":45.552789,"337":34.5400242,"338":38.2544472,"339":40.5865396,"340":45.6366228,"341":42.833014,"342":41.5874644,"343":33.3942655,"344":35.6869752,"345":37.0965278,"346":38.149576,"347":44.7971939,"348":38.8402805,"349":43.6830211,"350":42.4963416,"351":37.7252315,"352":42.5558381,"353":28.8052674,"354":40.4555157,"355":44.6621493,"356":48.1469683,"357":32.6926512,"358":46.0645809,"359":47.4234599,"360":46.7297771,"361":46.6020711,"362":13.444304,"363":15.1850483,"364":43.4799291,"365":41.223,"366":42.1292241,"367":37.3614238,"368":44.8994088,"369":44.3667876,"370":41.308274,"371":55.2062621,"372":41.2411897,"373":30.6953657,"374":37.648546,"375":39.9356016,"376":35.612661,"377":48.1469683,"378":43.9747838,"379":41.2574658,"380":35.1359386,"381":40.3977612,"382":29.9012437,"383":55.991561,"384":40.7371524,"385":29.7604267,"386":33.1580933,"387":41.7557501,"388":32.8406946,"389":39.7284944,"390":39.0473451,"391":42.224867,"392":37.6392595,"393":35.6468991,"394":32.792,"395":34.2576066,"396":34.6845455,"397":37.9374939,"398":34.1954331,"399":47.1301417,"400":34.1975048,"401":30.1588129,"402":34.5794343,"403":44.9428975,"404":35.1606822,"405":26.1420358,"406":24.726026,"407":39.0997265,"408":33.399661,"409":35.2626635,"410":44.0805434,"411":35.7344538,"412":36.3302284,"413":36.7280583,"414":20.8165975,"415":21.1675794,"416":31.1171194,"417":47.6587802,"418":33.4956744,"419":53.8725737},"longitude":{"0":-75.4714098,"1":-84.155741,"2":-70.099451,"3":-92.4451371,"4":-82.0105148,"5":-73.7562317,"6":-84.3876845,"7":-88.4153847,"8":-97.7430608,"9":-82.5514869,"10":-85.5872286,"11":-75.9179738,"12":-68.7712257,"13":-86.8103567,"14":-88.864698,"15":-86.7816016,"16":-71.0588801,"17":-81.4914894,"18":-91.1871466,"19":-73.212072,"20":-78.8783689,"21":-76.6121893,"22":-81.0348144,"23":-85.3093995,"24":-78.4766781,"25":-79.9310512,"26":-91.6656232,"27":-81.6943605,"28":-80.8431267,"29":-82.9987942,"30":-81.7373485,"31":-84.9877094,"32":-84.5120196,"33":-89.7031784,"34":-84.1916069,"35":-77.0368707,"36":-85.3904888,"37":-92.1004852,"38":-93.6249593,"39":-83.0457538,"40":-87.5710898,"41":-74.1723667,"42":-81.7841722,"43":-78.8783585,"44":-96.731265,"45":-85.1393513,"46":-82.3248262,"47":-89.0928155,"48":-85.6680863,"49":-79.9698685,"50":-82.2270568,"51":-88.4272627,"52":-73.7629097,"53":-77.8868117,"54":-86.158068,"55":-76.1804843,"56":-74.0059728,"57":-84.5555347,"58":-84.5037164,"59":-92.0198427,"60":-74.0059728,"61":-84.2472116,"62":-94.5785667,"63":-90.0489801,"64":-86.3077368,"65":-87.9064736,"66":-90.5151342,"67":-92.1193012,"68":-88.0398912,"69":-101.2922906,"70":-89.4007501,"71":-93.2650108,"72":-78.8866943,"73":-77.4302414,"74":-95.9345034,"75":-87.6297982,"76":-76.2858726,"77":-71.8022934,"78":-79.9958864,"79":-71.4128343,"80":-78.898619,"81":-77.4360481,"82":-79.9414266,"83":-77.6088465,"84":-92.4801989,"85":-81.091203,"86":-86.2519898,"87":-85.7584557,"88":-93.2922989,"89":-93.7501789,"90":-90.1994042,"91":-76.1474244,"92":-84.2807329,"93":-82.4081969,"94":-85.6206317,"95":-83.9207392,"96":-83.2784851,"97":-94.1605839,"98":-106.650422,"99":-101.8312969,"100":-149.8996785,"101":-75.9927652,"102":-72.6733723,"103":-116.2023137,"104":-118.3089661,"105":-111.0319925,"106":-104.8213634,"107":-104.990251,"108":-96.9209135,"109":-106.8265908,"110":-106.4850217,"111":-123.0867536,"112":-119.7871247,"113":-114.3168131,"114":-80.1373174,"115":-117.4260466,"116":-157.8581401,"117":-77.0368707,"118":-95.3698028,"119":-97.330053,"120":-81.655651,"121":-155.9962255,"122":-115.1391009,"123":-118.2436849,"124":-101.8551665,"125":-159.3672769,"126":-92.2880157,"127":-81.3789269,"128":-76.8867008,"129":-98.1775638,"130":-80.1917902,"131":-113.9940314,"132":-90.0715323,"133":-156.4728725,"134":-97.5164276,"135":-117.6508876,"136":-80.0533746,"137":-122.6783853,"138":-75.1652215,"139":-112.0740373,"140":-87.2169149,"141":-116.5452921,"142":-70.2568189,"143":-119.8142691,"144":-81.8723084,"145":-117.1610838,"146":-98.4945922,"147":-119.6981901,"148":-122.3320708,"149":-122.4194155,"150":-121.8852525,"151":-66.1184593,"152":-111.8910474,"153":-121.4943996,"154":-117.867653,"155":-82.5310117,"156":-64.9307007,"157":-64.7031977,"158":-82.4571776,"159":-95.992775,"160":-110.9741769,"161":-86.5027282,"162":-176.6217472,"163":-152.4072222,"164":-156.6627525,"165":-161.7694402,"166":-156.7886111,"167":-145.7525414,"168":-96.7969879,"169":-158.4633056,"170":-147.7199756,"171":-135.7389018,"172":-134.4201306,"173":-131.6461111,"174":-122.2711639,"175":-165.4086406,"176":-162.5930667,"177":-122.2020794,"178":-132.9574182,"179":-148.4597191,"180":-135.3345513,"181":-132.3815263,"182":-139.7268441,"183":-67.1540698,"184":-70.2881124,"185":-70.645473,"186":-66.6140616,"187":-108.5006904,"188":-81.0228331,"189":-85.6602058,"190":-96.7898034,"191":-88.0132958,"192":-95.3698028,"193":-86.5861037,"194":-112.0407584,"195":-90.8745758,"196":-87.6297982,"197":-80.6081089,"198":-100.8895761,"199":-93.2185144,"200":-107.8800667,"201":-108.5506486,"202":-97.6311006,"203":-75.5483909,"204":-73.2103934,"205":-74.0104178,"206":-74.759717,"207":-112.0740373,"208":-122.4786854,"209":-89.9839935,"210":-81.5190053,"211":-80.1425781,"212":-76.8926215,"213":-83.6874562,"214":-97.0328547,"215":-98.3420118,"216":-111.3007715,"217":-77.7199932,"218":-81.3526016,"219":-79.0377388,"220":-82.9987942,"221":-99.5075519,"222":-122.8755949,"223":-121.8946761,"224":-87.1111676,"225":-73.4529124,"226":-82.0453664,"227":-89.5889864,"228":-82.6402915,"229":-119.119948,"230":-70.7625532,"231":-111.6585337,"232":-103.2310149,"233":-121.3153096,"234":-89.0939952,"235":-77.8600012,"236":-121.2907796,"237":-81.269453,"238":-120.4357191,"239":-89.6501481,"240":-94.1632404,"241":-83.5378674,"242":-80.579511,"243":-155.084887,"244":-118.1937395,"245":-170.7020359,"246":-99.7331439,"247":-97.1466695,"248":-92.3425775,"249":-119.0187125,"250":-94.1265562,"251":-97.4974838,"252":-96.4929797,"253":-88.2433829,"254":-92.3340724,"255":-97.396381,"256":-90.6677347,"257":-100.8958674,"258":-94.4209646,"259":-100.8726618,"260":-94.7404891,"261":-97.7277959,"262":-80.752608,"263":-98.4184224,"264":-93.2173758,"265":-91.2519017,"266":-102.2522487,"267":-96.5716694,"268":-87.3953713,"269":-120.6596156,"270":-100.4370375,"271":-98.4933873,"272":-122.7140548,"273":-97.0583681,"274":-94.0361745,"275":-95.3010624,"276":-74.4229266,"277":-79.3794811,"278":-71.4547891,"279":-77.0441143,"280":-79.1422464,"281":-76.7074571,"282":-98.4864829,"283":-124.1065825,"284":-105.8700214,"285":-83.4327528,"286":-106.8175387,"287":-103.6671662,"288":-94.8826861,"289":-94.2020084,"290":-112.5347776,"291":-113.0618931,"292":-89.5181476,"293":-84.3475876,"294":-88.5809563,"295":-109.5498395,"296":-109.0565308,"297":-106.2980824,"298":-104.8202462,"299":-100.0170787,"300":-88.9548001,"301":-102.7896242,"302":-98.8651202,"303":-99.0816784,"304":-91.4984941,"305":-115.7631232,"306":-87.0645801,"307":-111.651302,"308":-94.1680158,"309":-105.5022205,"310":-106.9253207,"311":-107.2636842,"312":-92.9376887,"313":-112.0391057,"314":-103.1360403,"315":-99.3267702,"316":-88.0720706,"317":-93.4040679,"318":-94.513281,"319":-98.7084357,"320":-78.9219698,"321":-105.5911007,"322":-100.7601454,"323":-100.920999,"324":-96.7025955,"325":-80.4456303,"326":-117.0011889,"327":-93.2010367,"328":-88.703656,"329":-86.2483921,"330":-107.8761738,"331":-75.4863364,"332":-124.2242803,"333":-88.6000478,"334":-89.2903392,"335":-112.4506191,"336":-84.7839364,"337":-112.4685025,"338":-104.6091409,"339":-122.3916754,"340":-89.4120753,"341":-108.7306725,"342":-109.2029043,"343":-104.5230242,"344":-105.937799,"345":-113.5684164,"346":-79.0716958,"347":-106.9561791,"348":-97.6114237,"349":-114.3596191,"350":-96.4049408,"351":-92.1646722,"352":-114.4700518,"353":-97.0035982,"354":-109.5287479,"355":-111.1041092,"356":-103.6179745,"357":-114.6276916,"358":-118.3430209,"359":-120.3103494,"360":-117.1817377,"361":-120.5058987,"362":144.793731,"363":145.7467259,"364":-110.7624282,"365":-111.9738304,"366":-80.085059,"367":-118.3996636,"368":-97.1150732,"369":-100.3537522,"370":-72.9278835,"371":-162.7174221,"372":-77.0010786,"373":-88.0398912,"374":-118.972079,"375":-91.4098726,"376":-77.3663538,"377":-103.6179745,"378":-75.9107565,"379":-80.6671886,"380":-114.5285981,"381":-105.0749801,"382":-81.3124341,"383":-133.463631,"384":-114.0375102,"385":-95.3698028,"386":-117.3505939,"387":-124.2025913,"388":-83.6324022,"389":-121.8374777,"390":-95.6751576,"391":-121.7816704,"392":-120.9970014,"393":-117.8125674,"394":-115.5630514,"395":-88.7033859,"396":-90.3828769,"397":-107.8122852,"398":-79.7625625,"399":-119.2780771,"400":-119.1770516,"401":-85.6602058,"402":-118.1164613,"403":-123.0350963,"404":-79.4174178,"405":-81.7948103,"406":-81.0446262,"407":-94.5785667,"408":-91.0377029,"409":-77.5816353,"410":-103.2310149,"411":-81.3444573,"412":-119.2920585,"413":-108.2186856,"414":-156.9273193,"415":-157.0686307,"416":-97.7277959,"417":-117.4260466,"418":-88.4272627,"419":-166.5375512}}